{
  "uci": {
    "note": "UCI SMS Spam Collection (ham+spam).",
    "url": "https://archive.ics.uci.edu/ml/machine-learning-databases/00228/smsspamcollection.zip",
    "file": "SMSSpamCollection"
  },
  "smishtank": {
    "note": "SmishTank CSV (positives). Provide a direct CSV url or local path.",
    "url": "",
    "path": ""
  },
  "spamdam": {
    "note": "SpamDam CSV (positives). Provide a direct CSV url or local path.",
    "url": "",
    "path": ""
  },
  "nus": {
    "note": "NUS SMS Corpus (ham). Usually manual download due to license.",
    "url": "",
    "path": ""
  }
}


-- not used in the end files where just dragged in manually 